games_in_python/__init__.py
games_in_python/guessing.py
games_in_python/hangman.py
games_in_python-0.0.1.dist-info/METADATA
games_in_python-0.0.1.dist-info/WHEEL
games_in_python-0.0.1.dist-info/top_level.txt
games_in_python-0.0.1.dist-info/RECORD
