Metadata-Version: 2.1
Name: games_in_python
Version: 0.0.1
Summary: A package with some games in python
Home-page: https://github.com/PedroThezi/package-games-in-python
Author: Pedro Thezi
Author-email: pedro.maschieto130@gmail.com
Requires-Python: >=3.8
